darshan_mongodb_automation/__init__.py
darshan_mongodb_automation/mongo_crud.py
darshan_mongodb_automation-0.0.41.dist-info/METADATA
darshan_mongodb_automation-0.0.41.dist-info/WHEEL
darshan_mongodb_automation-0.0.41.dist-info/top_level.txt
darshan_mongodb_automation-0.0.41.dist-info/RECORD
