Metadata-Version: 2.1
Name: darshan_mongodb_automation
Version: 0.0.41
Summary: A python package for connecting to mongodb
Home-page: https://github.com/DarshanRokkad/MongoDB_Connector_Package
Author: DarshanRM
Author-email: darshanrokkad2003@gmail.com
License: MIT
Project-URL: Bug Tracker, https://github.com/DarshanRokkad/MongoDB_Connector_Package/issues
Classifier: Programming Language :: Python :: 3.8
Classifier: Programming Language :: Python :: 3.9
Classifier: Operating System :: OS Independent
Requires-Python: >=3.7
Requires-Dist: pymongo
Requires-Dist: pymongo[srv]
Requires-Dist: dnspython
Requires-Dist: pandas
Requires-Dist: numpy
Requires-Dist: ensure
Requires-Dist: pytest
Requires-Dist: tox
Requires-Dist: black
Requires-Dist: flake8
Requires-Dist: mypy
Provides-Extra: testing
Requires-Dist: pytest >=7.1.3 ; extra == 'testing'
Requires-Dist: mypy >=0.971 ; extra == 'testing'
Requires-Dist: flake8 >=5.0.4 ; extra == 'testing'
Requires-Dist: tox >=3.25.1 ; extra == 'testing'
Requires-Dist: black >=22.8.0 ; extra == 'testing'
